wechat_auto/__init__.py
wechat_auto/components/AI.py
wechat_auto/components/__init__.py
wechat_auto/components/weather.py
wechat_auto-0.8.2.dist-info/DESCRIPTION.rst
wechat_auto-0.8.2.dist-info/METADATA
wechat_auto-0.8.2.dist-info/RECORD
wechat_auto-0.8.2.dist-info/WHEEL
wechat_auto-0.8.2.dist-info/metadata.json
wechat_auto-0.8.2.dist-info/top_level.txt
