Metadata-Version: 2.0
Name: wechat-auto
Version: 0.8.2
Summary: A wechat chatroom auto reply and sent message robot
Home-page: https://github.com/true1023/wechat_auto
Author: Qinluo
Author-email: shi12li12@gmail.com
License: UNKNOWN
Platform: UNKNOWN
Classifier: Programming Language :: Python :: 3
Classifier: License :: OSI Approved :: MIT License
Classifier: Operating System :: OS Independent
